GEOMINE.py
GEOMINE-0.0.1.dist-info/LICENSE
GEOMINE-0.0.1.dist-info/METADATA
GEOMINE-0.0.1.dist-info/WHEEL
GEOMINE-0.0.1.dist-info/top_level.txt
GEOMINE-0.0.1.dist-info/RECORD
