Metadata-Version: 2.1
Name: GEOMINE
Version: 0.0.1
Summary: Orbits generator for colored directed graphs and orbits frequency finder
Classifier: Programming Language :: Python :: 3
Classifier: License :: OSI Approved :: MIT License
Classifier: Operating System :: OS Independent
Requires-Python: >=3.6
License-File: LICENSE
Requires-Dist: numpy
Requires-Dist: scipy
